d2x/__init__.py
d2x/api.py
d2x/auth/__init__.py
d2x/auth/sf/__init__.py
d2x/auth/sf/auth_url.py
d2x/auth/sf/login_url.py
d2x/base/models.py
d2x/base/types.py
d2x/cli/__init__.py
d2x/cli/main.py
d2x/env/__init__.py
d2x/gen/__init__.py
d2x/gen/sf/__init__.py
d2x/gen/sf/login_url.py
d2x/models/__init__.py
d2x/models/sf/__init__.py
d2x/models/sf/auth.py
d2x/models/sf/org.py
d2x/parse/__init__.py
d2x/parse/sf/__init__.py
d2x/parse/sf/auth_url.py
d2x/ux/cci.py
d2x/ux/gh/actions.py
d2x-0.1.3.dist-info/LICENSE
d2x-0.1.3.dist-info/METADATA
d2x-0.1.3.dist-info/WHEEL
d2x-0.1.3.dist-info/entry_points.txt
d2x-0.1.3.dist-info/RECORD
